craftax/__init__.py
craftax/craftax_env.py
craftax/craftax/__init__.py
craftax/craftax/constants.py
craftax/craftax/craftax_state.py
craftax/craftax/game_logic.py
craftax/craftax/play_craftax.py
craftax/craftax/renderer.py
craftax/craftax/assets/0.png
craftax/craftax/assets/1.png
craftax/craftax/assets/2.png
craftax/craftax/assets/3.png
craftax/craftax/assets/4.png
craftax/craftax/assets/5.png
craftax/craftax/assets/6.png
craftax/craftax/assets/7.png
craftax/craftax/assets/8.png
craftax/craftax/assets/9.png
craftax/craftax/assets/arrow-down.png
craftax/craftax/assets/arrow-left.png
craftax/craftax/assets/arrow-right.png
craftax/craftax/assets/arrow-up.png
craftax/craftax/assets/arrow_fire_enchantment.png
craftax/craftax/assets/arrow_ice_enchantment.png
craftax/craftax/assets/bat.png
craftax/craftax/assets/book.png
craftax/craftax/assets/boots_fire_enchantment.png
craftax/craftax/assets/boots_ice_enchantment.png
craftax/craftax/assets/bow.png
craftax/craftax/assets/chest.png
craftax/craftax/assets/chestplate_fire_enchantment.png
craftax/craftax/assets/chestplate_ice_enchantment.png
craftax/craftax/assets/coal.png
craftax/craftax/assets/cow.png
craftax/craftax/assets/dagger.png
craftax/craftax/assets/debug-2.png
craftax/craftax/assets/debug-3.png
craftax/craftax/assets/debug.png
craftax/craftax/assets/debug_tile.png
craftax/craftax/assets/deep_thing.png
craftax/craftax/assets/dexterity.png
craftax/craftax/assets/diamond.png
craftax/craftax/assets/diamond_boots.png
craftax/craftax/assets/diamond_chestplate.png
craftax/craftax/assets/diamond_helmet.png
craftax/craftax/assets/diamond_pants.png
craftax/craftax/assets/diamond_pickaxe.png
craftax/craftax/assets/diamond_sword.png
craftax/craftax/assets/drink.png
craftax/craftax/assets/enchantment_table_fire.png
craftax/craftax/assets/enchantment_table_ice.png
craftax/craftax/assets/energy.png
craftax/craftax/assets/fence.png
craftax/craftax/assets/fire_elemental.png
craftax/craftax/assets/fire_grass.png
craftax-1.5.0.dist-info/licenses/LICENSE
craftax-1.5.0.dist-info/METADATA
craftax-1.5.0.dist-info/WHEEL
craftax-1.5.0.dist-info/entry_points.txt
craftax-1.5.0.dist-info/top_level.txt
craftax-1.5.0.dist-info/RECORD
