Metadata-Version: 2.4
Name: craftax
Version: 1.5.0
Summary: An open-world environment for training RL agents
Author-email: Michael Matthews <michael.matthews@eng.ox.ac.uk>
Project-URL: Homepage, https://github.com/MichaelTMatthews/Craftax
Project-URL: Issues, https://github.com/MichaelTMatthews/Craftax/issues
Classifier: Programming Language :: Python :: 3
Classifier: License :: OSI Approved :: MIT License
Classifier: Operating System :: OS Independent
Requires-Python: >=3.9
License-File: LICENSE
Requires-Dist: jax
Requires-Dist: flax
Requires-Dist: numpy
Requires-Dist: pygame
Requires-Dist: gymnax
Requires-Dist: chex
Requires-Dist: matplotlib
Requires-Dist: imageio
Provides-Extra: dev
Requires-Dist: black; extra == "dev"
Requires-Dist: pre-commit; extra == "dev"
Dynamic: license-file
